{
  "generated": "2025-12-22T21:58:03.462807",
  "optimization_results": {
    "flash_flood": {
      "sweep": [
        {
          "threshold": 0.1,
          "pod": 1.0,
          "far": 0.49442755825734547,
          "csi": 0.5055724417426545,
          "bias": 1.9779559118236474,
          "hss": 0.02589755156954251
        },
        {
          "threshold": 0.15,
          "pod": 1.0,
          "far": 0.4934010152284264,
          "csi": 0.5065989847715736,
          "bias": 1.9739478957915833,
          "hss": 0.029882028864003884
        },
        {
          "threshold": 0.2,
          "pod": 1.0,
          "far": 0.46744930629669157,
          "csi": 0.5325506937033084,
          "bias": 1.877755511022044,
          "hss": 0.12552857604906628
        },
        {
          "threshold": 0.25,
          "pod": 1.0,
          "far": 0.45995670995670995,
          "csi": 0.54004329004329,
          "bias": 1.8517034068136273,
          "hss": 0.15143915918602052
        },
        {
          "threshold": 0.3,
          "pod": 0.9979959919839679,
          "far": 0.4222737819025522,
          "csi": 0.5770567786790266,
          "bias": 1.7274549098196392,
          "hss": 0.2710555116191754
        },
        {
          "threshold": 0.35,
          "pod": 0.9979959919839679,
          "far": 0.4,
          "csi": 0.5992779783393501,
          "bias": 1.6633266533066133,
          "hss": 0.3348779610913594
        },
        {
          "threshold": 0.4,
          "pod": 0.8476953907815631,
          "far": 0.34923076923076923,
          "csi": 0.5826446280991735,
          "bias": 1.3026052104208417,
          "hss": 0.39436338197081755
        },
        {
          "threshold": 0.45,
          "pod": 0.7394789579158316,
          "far": 0.2984790874524715,
          "csi": 0.5625,
          "bias": 1.0541082164328657,
          "hss": 0.4260596897922616
        },
        {
          "threshold": 0.5,
          "pod": 0.717434869739479,
          "far": 0.2796780684104628,
          "csi": 0.5611285266457681,
          "bias": 0.9959919839679359,
          "hss": 0.43999327991935905
        },
        {
          "threshold": 0.55,
          "pod": 0.5731462925851704,
          "far": 0.19662921348314608,
          "csi": 0.5026362038664324,
          "bias": 0.7134268537074149,
          "hss": 0.4336737961065574
        },
        {
          "threshold": 0.6,
          "pod": 0.4589178356713427,
          "far": 0.22108843537414966,
          "csi": 0.40602836879432624,
          "bias": 0.5891783567134269,
          "hss": 0.32944746471092184
        }
      ],
      "optimal_threshold": 0.35,
      "optimal_pod": 0.998,
      "optimal_far": 0.4,
      "optimal_csi": 0.5993
    },
    "hurricane_ri": {
      "sweep": [
        {
          "threshold": 0.1,
          "pod": 1.0,
          "far": 0.7711598746081505,
          "csi": 0.22884012539184953,
          "bias": 4.36986301369863,
          "hss": 0.17685007963808175
        },
        {
          "threshold": 0.15,
          "pod": 1.0,
          "far": 0.7550335570469798,
          "csi": 0.24496644295302014,
          "bias": 4.082191780821918,
          "hss": 0.2077018423573159
        },
        {
          "threshold": 0.2,
          "pod": 1.0,
          "far": 0.6826086956521739,
          "csi": 0.3173913043478261,
          "bias": 3.1506849315068495,
          "hss": 0.3342944369063771
        },
        {
          "threshold": 0.25,
          "pod": 1.0,
          "far": 0.6481927710843374,
          "csi": 0.35180722891566263,
          "bias": 2.8424657534246576,
          "hss": 0.3883861579737166
        },
        {
          "threshold": 0.3,
          "pod": 0.9863013698630136,
          "far": 0.6335877862595419,
          "csi": 0.36455696202531646,
          "bias": 2.691780821917808,
          "hss": 0.4083593403795929
        },
        {
          "threshold": 0.35,
          "pod": 0.9383561643835616,
          "far": 0.5566343042071198,
          "csi": 0.4308176100628931,
          "bias": 2.1164383561643834,
          "hss": 0.5037996337438181
        },
        {
          "threshold": 0.4,
          "pod": 0.8287671232876712,
          "far": 0.5291828793774319,
          "csi": 0.42907801418439717,
          "bias": 1.7602739726027397,
          "hss": 0.5090804864067131
        },
        {
          "threshold": 0.45,
          "pod": 0.5821917808219178,
          "far": 0.4178082191780822,
          "csi": 0.4106280193236715,
          "bias": 1.0,
          "hss": 0.5107632093933465
        },
        {
          "threshold": 0.5,
          "pod": 0.5205479452054794,
          "far": 0.3870967741935484,
          "csi": 0.3917525773195876,
          "bias": 0.8493150684931506,
          "hss": 0.49527785381877915
        },
        {
          "threshold": 0.55,
          "pod": 0.363013698630137,
          "far": 0.3375,
          "csi": 0.3063583815028902,
          "bias": 0.547945205479452,
          "hss": 0.4078168180023687
        },
        {
          "threshold": 0.6,
          "pod": 0.2328767123287671,
          "far": 0.2916666666666667,
          "csi": 0.2125,
          "bias": 0.3287671232876712,
          "hss": 0.29993777224642204
        }
      ],
      "optimal_threshold": 0.35,
      "optimal_pod": 0.9384,
      "optimal_far": 0.5566,
      "optimal_csi": 0.4308
    },
    "gic": {
      "sweep": [
        {
          "threshold": 0.1,
          "pod": 1.0,
          "far": 0.5445344129554656,
          "csi": 0.45546558704453444,
          "bias": 2.1955555555555555,
          "hss": 0.019679300291545212
        },
        {
          "threshold": 0.15,
          "pod": 1.0,
          "far": 0.5351239669421488,
          "csi": 0.46487603305785125,
          "bias": 2.151111111111111,
          "hss": 0.05267008046817852
        },
        {
          "threshold": 0.2,
          "pod": 1.0,
          "far": 0.5187165775401069,
          "csi": 0.48128342245989303,
          "bias": 2.077777777777778,
          "hss": 0.10763569457221711
        },
        {
          "threshold": 0.25,
          "pod": 1.0,
          "far": 0.504950495049505,
          "csi": 0.49504950495049505,
          "bias": 2.02,
          "hss": 0.151414309484193
        },
        {
          "threshold": 0.3,
          "pod": 0.9866666666666667,
          "far": 0.4657039711191336,
          "csi": 0.5304659498207885,
          "bias": 1.8466666666666667,
          "hss": 0.2628024760832865
        },
        {
          "threshold": 0.35,
          "pod": 0.9155555555555556,
          "far": 0.4340659340659341,
          "csi": 0.5378590078328982,
          "bias": 1.6177777777777778,
          "hss": 0.32287681713848515
        },
        {
          "threshold": 0.4,
          "pod": 0.8577777777777778,
          "far": 0.3987538940809969,
          "csi": 0.546742209631728,
          "bias": 1.4266666666666667,
          "hss": 0.37767405678724225
        },
        {
          "threshold": 0.45,
          "pod": 0.7133333333333334,
          "far": 0.3141025641025641,
          "csi": 0.5376884422110553,
          "bias": 1.04,
          "hss": 0.4444444444444445
        },
        {
          "threshold": 0.5,
          "pod": 0.7022222222222222,
          "far": 0.29933481152993346,
          "csi": 0.5401709401709401,
          "bias": 1.0022222222222221,
          "hss": 0.45667541910725107
        },
        {
          "threshold": 0.55,
          "pod": 0.4911111111111111,
          "far": 0.21071428571428572,
          "csi": 0.43418467583497056,
          "bias": 0.6222222222222222,
          "hss": 0.39748953974895396
        },
        {
          "threshold": 0.6,
          "pod": 0.44,
          "far": 0.21428571428571427,
          "csi": 0.39285714285714285,
          "bias": 0.56,
          "hss": 0.35606060606060613
        }
      ],
      "optimal_threshold": 0.4,
      "optimal_pod": 0.8578,
      "optimal_far": 0.3988,
      "optimal_csi": 0.5467
    }
  }
}